sxcu/__client__.py
sxcu/__init__.py
sxcu/__logger__.py
sxcu/__main__.py
sxcu/__version__.py
sxcu/_cli.py
sxcu/_utils.py
sxcu/constants.py
sxcu/exceptions.py
sxcu/og_properties.py
sxcu/sxcu.py
sxcu-4.1.0.dist-info/entry_points.txt
sxcu-4.1.0.dist-info/LICENSE
sxcu-4.1.0.dist-info/WHEEL
sxcu-4.1.0.dist-info/METADATA
sxcu-4.1.0.dist-info/RECORD
