Metadata-Version: 2.1
Name: sxcu
Version: 4.1.0
Summary: Python API wrapper for sxcu.net
Home-page: https://github.com/naveen521kk/sxcu
License: Apache-2.0
Keywords: api,sxcu,sharex
Author: Naveen M K
Author-email: naveen521kk@gmail.com
Maintainer: Naveen M K
Maintainer-email: naveen521kk@gmail.com
Requires-Python: >=3.6,<4.0
Classifier: Development Status :: 4 - Beta
Classifier: License :: OSI Approved :: Apache Software License
Classifier: Operating System :: OS Independent
Classifier: Programming Language :: Python :: 3
Classifier: Programming Language :: Python :: 3.10
Classifier: Programming Language :: Python :: 3.6
Classifier: Programming Language :: Python :: 3.7
Classifier: Programming Language :: Python :: 3.8
Classifier: Programming Language :: Python :: 3.9
Classifier: Topic :: Internet
Provides-Extra: cli
Requires-Dist: pyperclip (>=1.8,<2.0); extra == "cli"
Requires-Dist: requests (>=2.0.0)
Requires-Dist: rich (>=10.5,<11.0); extra == "cli"
Project-URL: Documentation, https://sxcu.readthedocs.io/en/latest
Project-URL: Repository, https://github.com/naveen521kk/sxcu
